stringstranslate/__init__.py
stringstranslate/exceptions.py
stringstranslate/strings_translator.py
strings_translate-1.0.3.dist-info/LICENSE
strings_translate-1.0.3.dist-info/METADATA
strings_translate-1.0.3.dist-info/WHEEL
strings_translate-1.0.3.dist-info/top_level.txt
strings_translate-1.0.3.dist-info/RECORD
