Metadata-Version: 2.1
Name: strings-translate
Version: 1.0.3
Summary: A package for automatic translation of .strings files using the Google Translate API
Home-page: https://github.com/matyasbohacek/strings-translate
Author: Matyáš Boháček
Author-email: matyas.bohacek@matsworld.io
License: UNKNOWN
Platform: UNKNOWN
Classifier: Programming Language :: Python :: 3
Classifier: License :: OSI Approved :: MIT License
Classifier: Operating System :: OS Independent
Requires-Python: >=3.7
